page_monitor
