Metadata-Version: 2.1
Name: page-monitor
Version: 0.4
Summary: Simple Python based Page monitoring with JS support and notifications
Home-page: https://github.com/MarcDufresne/page-monitor
Author: MarcDufresne
Author-email: marc.andre.dufresne@gmail.com
License: MIT
Keywords: page-monitor monitoring website-monitor email telegram-messages mailgun smtp telegram
Platform: UNKNOWN
Classifier: Development Status :: 4 - Beta
Classifier: Environment :: Console
Classifier: Intended Audience :: Developers
Classifier: Intended Audience :: End Users/Desktop
Classifier: License :: OSI Approved :: MIT License
Classifier: Operating System :: MacOS :: MacOS X
Classifier: Operating System :: Unix
Classifier: Programming Language :: Python :: 3.6
Classifier: Topic :: Internet
Classifier: Topic :: Utilities
